moodys_custom_operations/__init__.py
moodys_custom_operations/operations.py
moodys_custom_operations-0.0.3.dist-info/LICENSE.txt
moodys_custom_operations-0.0.3.dist-info/METADATA
moodys_custom_operations-0.0.3.dist-info/WHEEL
moodys_custom_operations-0.0.3.dist-info/top_level.txt
moodys_custom_operations-0.0.3.dist-info/RECORD
