Metadata-Version: 2.1
Name: moodys-custom-operations
Version: 0.0.3
Summary: Some useful arithmetic and boolean operations
Home-page: https://www.moodys.com/
Author: Subhajit Ganguli
Author-email: subhajit.ganguli-non-empl@moodys.com
License: UNKNOWN
Platform: UNKNOWN
Classifier: Programming Language :: Python :: 3
Classifier: License :: OSI Approved :: MIT License
Classifier: Operating System :: OS Independent
Requires-Python: >=3.6
